loki_logging_handler/__init__.py
loki_logging_handler/loki_client.py
loki_logging_handler/loki_handler.py
loki_logging_handler/models.py
loki_logging_handler/formatters/__init__.py
loki_logging_handler/formatters/json_formatter.py
tests/__init__.py
tests/test_json_formatter.py
tests/test_loki_logger_handler.py
loki_logging_handler-0.0.5.dist-info/LICENSE
loki_logging_handler-0.0.5.dist-info/METADATA
loki_logging_handler-0.0.5.dist-info/WHEEL
loki_logging_handler-0.0.5.dist-info/top_level.txt
loki_logging_handler-0.0.5.dist-info/RECORD
