Metadata-Version: 2.1
Name: loki-logging-handler
Version: 0.0.5
Summary: Logging handler to send logs to Grafana Loki
Home-page: https://github.com/fuyufjh/loki_logging_handler
Author: Eric Fu
License: MIT
Keywords: loki,logging,handler
Classifier: Development Status :: 3 - Alpha
Classifier: Intended Audience :: Developers
Classifier: License :: OSI Approved :: MIT License
Classifier: Programming Language :: Python :: 3
Classifier: Programming Language :: Python :: 3.6
Classifier: Programming Language :: Python :: 3.7
Classifier: Programming Language :: Python :: 3.8
Classifier: Programming Language :: Python :: 3.9
Classifier: Programming Language :: Python :: 3.10
Classifier: Programming Language :: Python :: 3.11
Classifier: Programming Language :: Python :: 3.12
Requires-Python: >=3.6
License-File: LICENSE
Requires-Dist: requests ==2.28.2
